fluxdataqaqc/__init__.py
fluxdataqaqc/data.py
fluxdataqaqc/plot.py
fluxdataqaqc/qaqc.py
fluxdataqaqc/util.py
fluxdataqaqc-0.2.2.dist-info/LICENSE.txt
fluxdataqaqc-0.2.2.dist-info/METADATA
fluxdataqaqc-0.2.2.dist-info/WHEEL
fluxdataqaqc-0.2.2.dist-info/top_level.txt
fluxdataqaqc-0.2.2.dist-info/RECORD
