Metadata-Version: 2.1
Name: fluxdataqaqc
Version: 0.2.2
Summary: Tools for QA/QC of eddy covariance station data
Home-page: https://github.com/Open-ET/flux-data-qaqc
Author: John Volk
Author-email: john.volk@dri.edu
License: BSD3
Platform: Windows
Platform: Linux
Platform: Mac OS X
Classifier: License :: OSI Approved :: BSD License
Classifier: Programming Language :: Python :: 3.7
Classifier: Environment :: Console
Classifier: Development Status :: 4 - Beta
Classifier: Topic :: Scientific/Engineering
Classifier: Intended Audience :: Science/Research
Requires-Python: >=3.7
License-File: LICENSE.txt
Requires-Dist: bokeh >=3
Requires-Dist: netCDF4
Requires-Dist: numpy >=1.15
Requires-Dist: pandas >=1.0
Requires-Dist: refet ==0.3.10
Requires-Dist: scikit-learn
Requires-Dist: xarray
Requires-Dist: openpyxl
